apyds/__init__.py
apyds/_ds.cpython-314-x86_64-linux-musl.so
apyds/_ds.pyi
apyds/buffer_size.py
apyds/common.py
apyds/ds.py
apyds/item_t.py
apyds/list_t.py
apyds/py.typed
apyds/rule_t.py
apyds/search_t.py
apyds/string_t.py
apyds/term_t.py
apyds/variable_t.py
apyds.libs/libgcc_s-0cd532bd.so.1
apyds.libs/libstdc++-5d72f927.so.6.0.33
apyds-0.0.14.dist-info/METADATA
apyds-0.0.14.dist-info/WHEEL
apyds-0.0.14.dist-info/RECORD
apyds-0.0.14.dist-info/licenses/LICENSE.md
apyds-0.0.14.dist-info/sboms/auditwheel.cdx.json
