Metadata-Version: 2.4
Name: apyds
Version: 0.0.14
Summary: A deductive system
Author-Email: Hao Zhang <hzhangxyz@outlook.com>
License-Expression: AGPL-3.0-or-later
Project-URL: Repository, https://github.com/USTC-KnowledgeComputingLab/ds.git
Requires-Python: <3.15,>=3.11
Provides-Extra: dev
Requires-Dist: ruff~=0.14.10; extra == "dev"
Requires-Dist: pytest~=9.0.2; extra == "dev"
Requires-Dist: pytest-cov~=7.0.0; extra == "dev"
Provides-Extra: docs
Requires-Dist: mkdocs~=1.6.1; extra == "docs"
Requires-Dist: mkdocs-material~=9.7.1; extra == "docs"
Requires-Dist: mike~=2.1.3; extra == "docs"
